{"cameraMode":{"drawMode":0,"name":"Shaded","section":"Shading Mode"},"sceneLighting":true,"audioPlay":false,"sceneViewState":{"m_AlwaysRefresh":false,"showFog":true,"showSkybox":true,"showFlares":true,"showImageEffects":true,"showParticleSystems":true,"showVisualEffectGraphs":true,"m_FxEnabled":true},"in2DMode":false,"pivot":{"x":-6.19999885559082,"y":-5.800000190734863,"z":-2.700000762939453},"rotation":{"x":-0.02198227122426033,"y":0.974160373210907,"z":-0.10888279229402542,"w":-0.19665902853012086},"size":37.38409423828125,"orthographic":false}